MANIFEST.in
README.rst
setup.cfg
setup.py
django_fields_bundle.egg-info/PKG-INFO
django_fields_bundle.egg-info/SOURCES.txt
django_fields_bundle.egg-info/dependency_links.txt
django_fields_bundle.egg-info/not-zip-safe
django_fields_bundle.egg-info/requires.txt
django_fields_bundle.egg-info/top_level.txt
fields_bundle/__init__.py
fields_bundle/version.py
fields_bundle/fields/__init__.py
fields_bundle/fields/colors.py
fields_bundle/fields/files.py
fields_bundle/fields/icons.py
fields_bundle/fields/images.py
fields_bundle/fields/prices.py
fields_bundle/fields/subclassing.py
fields_bundle/fields/uuid_field.py
fields_bundle/forms/__init__.py
fields_bundle/forms/colors.py
fields_bundle/forms/dates.py
fields_bundle/forms/geo.py
fields_bundle/forms/icons.py
fields_bundle/forms/images.py
fields_bundle/forms/phone.py
fields_bundle/forms/prices.py
fields_bundle/forms/zipcode.py