Metadata-Version: 1.1
Name: django-fields-bundle
Version: 1.0.7
Summary: Django extra fields bundle
Home-page: http://github.com/dalou/django-fields-bundle
Author: Autrusseau Damien
Author-email: autrusseau.damien@gmail.com
License: MIT
Platform: UNKNOWN
Classifier: Development Status :: 5 - Production/Stable
Classifier: Environment :: Web Environment
Classifier: Intended Audience :: Developers
Classifier: License :: OSI Approved :: BSD License
Classifier: Operating System :: OS Independent
Classifier: Programming Language :: Python
Classifier: Framework :: Django
